setup.py
futures_then/__init__.py
futures_then/futures_then.py
futures_then.egg-info/PKG-INFO
futures_then.egg-info/SOURCES.txt
futures_then.egg-info/dependency_links.txt
futures_then.egg-info/requires.txt
futures_then.egg-info/top_level.txt